{
    "level00": [
        {
            "title": "HTML",
            "summary": "U02S2PS9C",
            "url": "http://www.google.nl"
        },
        {
            "title": "CSS",
            "summary": "U02S2PS9C",
            "url": "http://www.google.nl"
        },
        {
            "title": "Gists",
            "summary": "U02S2PS9C",
            "url": "http://www.google.nl"
        }
    ],
    "level01": [
        {
            "title": "Bladiebla",
            "summary": "U02S2PS9C",
            "url": "http://www.google.nl"
        },
        {
            "title": "Bladiebla",
            "summary": "U02S2PS9C",
            "url": "http://www.google.nl"
        },
        {
            "title": "Bladiebla",
            "summary": "U02S2PS9C",
            "url": "http://www.google.nl"
        }
    ]

}